llama_index/tools/elevenlabs/__init__.py
llama_index/tools/elevenlabs/base.py
llama_index_tools_elevenlabs-0.2.1.dist-info/METADATA
llama_index_tools_elevenlabs-0.2.1.dist-info/WHEEL
llama_index_tools_elevenlabs-0.2.1.dist-info/licenses/LICENSE
llama_index_tools_elevenlabs-0.2.1.dist-info/RECORD
