Metadata-Version: 2.4
Name: llama-index-tools-elevenlabs
Version: 0.2.1
Summary: llama-index tools elevenlabs integration
Author-email: Your Name <you@example.com>
Maintainer: scummins00
License-Expression: MIT
License-File: LICENSE
Requires-Python: <4.0,>=3.9
Requires-Dist: elevenlabs<2,>=1.12.1
Requires-Dist: llama-index-core<0.15,>=0.13.0
